share_price_nepal/__init__.py
share_price_nepal/share_price_nepal.py
share_price_nepal-0.1.5.dist-info/METADATA
share_price_nepal-0.1.5.dist-info/WHEEL
share_price_nepal-0.1.5.dist-info/top_level.txt
share_price_nepal-0.1.5.dist-info/RECORD
